easyvar/__init__.py
easyvar/abc.py
easyvar/data.py
easyvar/defaults.py
easyvar/mixins.py
easyvar/prop.py
easyvar/test.py
easyvar/types.py
easyvar/unro.py
easyvar/utils.py
easyvar/version.py
easyvar-0.0.4.dist-info/LICENSE
easyvar-0.0.4.dist-info/METADATA
easyvar-0.0.4.dist-info/WHEEL
easyvar-0.0.4.dist-info/top_level.txt
easyvar-0.0.4.dist-info/RECORD
